Metadata-Version: 2.4
Name: adafruit-circuitpython-ssd1305
Version: 1.4.4
Summary: Framebuf (non-displayio) driver for SSD1305 displays
Author-email: Adafruit Industries <circuitpython@adafruit.com>
License: MIT
Project-URL: Homepage, https://github.com/adafruit/Adafruit_CircuitPython_SSD1305
Keywords: adafruit,blinka,circuitpython,micropython,ssd1305,framebuf,rpi
Classifier: Intended Audience :: Developers
Classifier: Topic :: Software Development :: Libraries
Classifier: Topic :: Software Development :: Embedded Systems
Classifier: Topic :: System :: Hardware
Classifier: License :: OSI Approved :: MIT License
Classifier: Programming Language :: Python :: 3
License-File: LICENSE
Requires-Dist: Adafruit-Blinka
Requires-Dist: adafruit-circuitpython-busdevice
Requires-Dist: adafruit-circuitpython-framebuf
Provides-Extra: optional
Dynamic: license-file
